slurmops/__init__.py
slurmops-0.0.1.dist-info/LICENSE
slurmops-0.0.1.dist-info/WHEEL
slurmops-0.0.1.dist-info/METADATA
slurmops-0.0.1.dist-info/RECORD
